pymongoose/__init__.py
pymongoose/logger.py
pymongoose/methods.py
pymongoose/mongo_types.py
pymongoose/version.py
pymongoose-1.3.7.dist-info/LICENSE
pymongoose-1.3.7.dist-info/METADATA
pymongoose-1.3.7.dist-info/WHEEL
pymongoose-1.3.7.dist-info/top_level.txt
pymongoose-1.3.7.dist-info/RECORD
