Metadata-Version: 2.1
Name: pymongoose
Version: 1.3.7
Summary: A pymongo helper with methods and classes
Home-page: https://github.com/djcharles26/pymongoose
Author: Juan Carlos Lara
Author-email: jlaraanaya@gmail.com
Classifier: Programming Language :: Python :: 3
Classifier: License :: OSI Approved :: MIT License
Classifier: Operating System :: OS Independent
Requires-Python: >=3.8
License-File: LICENSE
Requires-Dist: pymongo
